leuci_map/__init__.py
leuci_map/atom.py
leuci_map/mapfunctions.py
leuci_map/maploader.py
leuci_map/mapobject.py
leuci_map/mapplothelp.py
leuci_map/mapplotter.py
leuci_map/mapsmanager.py
leuci_map/pdbobject.py
leuci_map-0.1.65.dist-info/LICENSE
leuci_map-0.1.65.dist-info/METADATA
leuci_map-0.1.65.dist-info/WHEEL
leuci_map-0.1.65.dist-info/top_level.txt
leuci_map-0.1.65.dist-info/RECORD
