Metadata-Version: 2.1
Name: leuci-map
Version: 0.1.65
Summary: density maps library
Home-page: https://github.com/pypa/sampleproject
Author: Rachel Alcraft
Author-email: rachelalcraft@gmail.com
Project-URL: Bug Tracker, https://github.com/pypa/sampleproject/issues
Classifier: Programming Language :: Python :: 3
Classifier: License :: OSI Approved :: MIT License
Classifier: Operating System :: OS Independent
Requires-Python: >=3.6
License-File: LICENSE
